liturgical_calendar/__init__.py
liturgical_calendar/feasts.py
liturgical_calendar/funcs.py
liturgical_calendar/liturgical.py
liturgical_calendar-0.5.3.dist-info/METADATA
liturgical_calendar-0.5.3.dist-info/WHEEL
liturgical_calendar-0.5.3.dist-info/entry_points.txt
liturgical_calendar-0.5.3.dist-info/RECORD
