Metadata-Version: 2.4
Name: liturgical-calendar
Version: 0.5.3
Summary: Library to determine liturgical dates and colours for the Anglican Church of England
Author: Jonathan Gazeley
Author-email: me@jonathangazeley.com
Requires-Python: >=3.11,<4.0
Classifier: Programming Language :: Python :: 3
Classifier: Programming Language :: Python :: 3.11
Classifier: Programming Language :: Python :: 3.12
Classifier: Programming Language :: Python :: 3.13
Classifier: Programming Language :: Python :: 3.14
Requires-Dist: python-dateutil (>=2.8.2,<3.0.0)
